{"name":"kiểm tra nhập email \u003e 255 ký tự","id":"[engine:junit-jupiter]/[class:Test.Web.RegisterTest]/[method:checkInputUserEmailOverLength()]","scenarioId":"[engine:junit-jupiter]/[class:Test.Web.RegisterTest]","testCaseName":"Test.Web.RegisterTest","methodName":"checkInputUserEmailOverLength","testSteps":[{"number":1,"description":"truy cập trang đăng ký","duration":1991,"startTime":"2025-03-25T16:36:39.608219300Z[Europe/London]","screenshots":[{"screenshot":"a133df92da281fbc66d6aa3e272f270ef64d2d70b223a006efe7dd0471ca972a.png","timeStamp":1742920601599,"screenshotName":"a133df92da281fbc66d6aa3e272f270ef64d2d70b223a006efe7dd0471ca972a.png"}],"result":"SUCCESS","precondition":false,"level":0},{"number":2,"description":"xóa dữ liệu ô nhập","duration":502,"startTime":"2025-03-25T16:36:41.599876600Z[Europe/London]","screenshots":[{"screenshot":"a133df92da281fbc66d6aa3e272f270ef64d2d70b223a006efe7dd0471ca972a.png","timeStamp":1742920601599,"screenshotName":"a133df92da281fbc66d6aa3e272f270ef64d2d70b223a006efe7dd0471ca972a.png"}],"result":"SUCCESS","precondition":false,"level":0},{"number":3,"description":"nhập họ tên","duration":367,"startTime":"2025-03-25T16:36:42.101885800Z[Europe/London]","screenshots":[{"screenshot":"5657ac1b07cf7d3c47389e855205948b9dc159e7e99230bc73a60082e7b62ae4.png","timeStamp":1742920602469,"screenshotName":"5657ac1b07cf7d3c47389e855205948b9dc159e7e99230bc73a60082e7b62ae4.png"}],"result":"SUCCESS","precondition":false,"level":0},{"number":4,"description":"nhập số điện thoại","duration":428,"startTime":"2025-03-25T16:36:42.469435Z[Europe/London]","screenshots":[{"screenshot":"713988226fd6308db432e01fa9eebfba9e17d04afcf7e72eac645b20028d6aef.png","timeStamp":1742920602897,"screenshotName":"713988226fd6308db432e01fa9eebfba9e17d04afcf7e72eac645b20028d6aef.png"}],"result":"SUCCESS","precondition":false,"level":0},{"number":5,"description":"nhập địa chỉ email","duration":524,"startTime":"2025-03-25T16:36:42.897829400Z[Europe/London]","screenshots":[{"screenshot":"32e97484c2c554f56f033e44f23c2f241eb8001c22d11c84f4d161b3634f802e.png","timeStamp":1742920603422,"screenshotName":"32e97484c2c554f56f033e44f23c2f241eb8001c22d11c84f4d161b3634f802e.png"}],"result":"SUCCESS","precondition":false,"level":0},{"number":6,"description":"nhập tài khoản đăng nhập","duration":373,"startTime":"2025-03-25T16:36:43.422679800Z[Europe/London]","screenshots":[{"screenshot":"173764a47eb3935ed7a563022baa6ff12599ee87965e0f281683741c7fc5b3a8.png","timeStamp":1742920603795,"screenshotName":"173764a47eb3935ed7a563022baa6ff12599ee87965e0f281683741c7fc5b3a8.png"}],"result":"SUCCESS","precondition":false,"level":0},{"number":7,"description":"nhập mật khẩu","duration":36,"startTime":"2025-03-25T16:36:43.797708600Z[Europe/London]","screenshots":[{"screenshot":"173764a47eb3935ed7a563022baa6ff12599ee87965e0f281683741c7fc5b3a8.png","timeStamp":1742920603801,"screenshotName":"173764a47eb3935ed7a563022baa6ff12599ee87965e0f281683741c7fc5b3a8.png"}],"result":"SUCCESS","precondition":false,"level":0},{"number":8,"description":"nhập lại mật khẩu","duration":1132,"startTime":"2025-03-25T16:36:43.834423200Z[Europe/London]","screenshots":[{"screenshot":"5c5f3db42e87df113fdd6145c8a216bf3113c5b4e177e11d4006243abe1f7df6.png","timeStamp":1742920604634,"screenshotName":"5c5f3db42e87df113fdd6145c8a216bf3113c5b4e177e11d4006243abe1f7df6.png"},{"screenshot":"633adb4cd7a00de832e457cae0f720befe0f9d26055b29b7c26dd9d89f24bf50.png","timeStamp":1742920604966,"screenshotName":"633adb4cd7a00de832e457cae0f720befe0f9d26055b29b7c26dd9d89f24bf50.png"}],"result":"SUCCESS","precondition":false,"level":0},{"number":9,"description":"bấm nút đăng ký","duration":1236,"startTime":"2025-03-25T16:36:44.966729900Z[Europe/London]","screenshots":[{"screenshot":"b5ae10af4b8119e4f1e0ab7d6c8edc8969ea85acf0d63aa08b28cfcaf67433dd.png","timeStamp":1742920606198,"screenshotName":"b5ae10af4b8119e4f1e0ab7d6c8edc8969ea85acf0d63aa08b28cfcaf67433dd.png"}],"result":"SUCCESS","precondition":false,"level":0},{"number":10,"description":"kiểm tra hiển thị thông báo địa chỉ email không hợp lệ","duration":844,"startTime":"2025-03-25T16:36:46.204718900Z[Europe/London]","screenshots":[{"screenshot":"b5ae10af4b8119e4f1e0ab7d6c8edc8969ea85acf0d63aa08b28cfcaf67433dd.png","timeStamp":1742920606208,"screenshotName":"b5ae10af4b8119e4f1e0ab7d6c8edc8969ea85acf0d63aa08b28cfcaf67433dd.png"}],"result":"SUCCESS","precondition":false,"level":0}],"userStory":{"id":"Test.Web.RegisterTest","storyName":"RegisterTest","displayName":"RegisterTest","storyClassName":"Test.Web.RegisterTest","path":"Test.Web.RegisterTest","pathElements":[{"name":"Test","description":"Test"},{"name":"Web","description":"Web"},{"name":"RegisterTest","description":"RegisterTest"}],"narrative":"","type":"feature"},"title":"kiểm tra nhập email \u003e 255 ký tự","tags":[{"name":"Chrome","type":"context","displayName":"Chrome"},{"name":"Windows","type":"context","displayName":"Windows"},{"name":"Chrome, Windows","type":"context","displayName":"Chrome, Windows"}],"startTime":"2025-03-25T16:36:39.608219300Z[Europe/London]","duration":1208,"projectKey":"","sessionId":"603464597a28d52f8870c1b0411e0fc7","driver":"chrome","isManualTestingUpToDate":false,"context":"chrome,windows","manual":false,"testSource":"JUnit5","order":0,"result":"SUCCESS"}